dictstore/__init__.py
dictstore/exceptions.py
dictstore/file_handler.py
dictstore/helpers.py
dictstore/interface.py
dictstore-1.0.0.dist-info/LICENSE
dictstore-1.0.0.dist-info/METADATA
dictstore-1.0.0.dist-info/WHEEL
dictstore-1.0.0.dist-info/top_level.txt
dictstore-1.0.0.dist-info/RECORD
