Metadata-Version: 2.1
Name: dictstore
Version: 1.0.0
Summary: local datastore with a dictionary interface
Home-page: https://github.com/sampathbalivada/dictstore
Author: Sai Sampath Kumar Balivada
Author-email: balivadask2000@gmail.com
License: UNKNOWN
Project-URL: Bug Tracker, https://github.com/sampathbalivada/dictstore/issues
Platform: UNKNOWN
Classifier: Programming Language :: Python :: 3
Classifier: License :: OSI Approved :: Apache Software License
Classifier: Operating System :: OS Independent
Classifier: Development Status :: 5 - Production/Stable
Classifier: Topic :: Database
Requires-Python: >=3.6
License-File: LICENSE
